Workbook

Sheet Resumo
A1: Custo de produção: resumo
A2: Valores em R$. Atualize as abas azuis; esta página recalcula sozinha.
A4: Custo fixo mensal | B4: ='Custo Fixo'!B13 -> 1407.1
A5: Unidades produzidas por mês | B5: 100 | C5: Estimativa: troque pelo volume real do mês
A6: Custo fixo por unidade (rateio) | B6: =IF(B5>0,B4/B5,0) -> 14.071 | C6: Somar ao custo do produto na aba Ficha Técnica
A8: Pendências (custos ainda não incluídos)
A9: • Frete de compras pela internet
A10: • Produtos de limpeza e higienização
A11: • Despesas com entregas e transporte
A12: • Manutenção e reposição de materiais
A13: • Pró-labore ou retiradas pessoais
A14: • Temperos diversos: quantidade não informada
A15: • Papel-manteiga, filme plástico e papel-alumínio: tamanho do rolo não informado
A17: Observações
A18: • 'Insumos de produção' (R$ 122,94/semana) pode repetir compras da lista de insumos; confira antes de somar.
A19: • Farinha de trigo e cream cheese aparecem uma vez só, com o mesmo preço usado nas duas seções originais.
A20: • Preços sem frete. Atualize as abas Insumos e Embalagens quando o preço mudar.

Sheet Custo Fixo
A1: Custo fixo mensal
A2: Valores em R$. Células azuis são entradas; preto são fórmulas.
A4: Despesa | B4: Valor mensal (R$) | C4: Observação
A5: Água | B5: 77 | C5: Informado
A6: Energia elétrica | B6: 362.56 | C6: Informado
A7: Gás de cozinha | B7: 110 | C7: Informado
A8: DAS | B8: 86 | C8: Informado
A9: Taxas de máquina de cartão | B9: 238.8 | C9: Média informada
A10: Insumos de produção (por semana) | B10: 122.94 | C10: Informado por semana; convertido para mês abaixo
A11: Semanas por ano | B11: 52 | C11: Constante de conversão
A12: Insumos de produção (por mês) | B12: =B10*B11/12 -> 532.74 | C12: Semanal × 52 ÷ 12
A13: TOTAL CUSTO FIXO MENSAL | B13: =SUM(B5:B9)+B12 -> 1407.1 | C13: Não inclui itens 'a levantar' (ver Resumo)

Sheet Insumos
A1: Insumos: custo unitário
A2: Custo por unidade = Preço ÷ Quantidade da embalagem. Unidade: g, ml ou un. Deixe a quantidade vazia quando não souber.
A4: Categoria | B4: Insumo | C4: Qtd na embalagem | D4: Unidade | E4: Preço (R$) | F4: Custo por unidade (R$) | G4: Custo por 100 g/ml (R$)
A5: Doces e bolos | B5: Leite condensado | C5: 395 | D5: g | E5: 7.79 | F5: =IF(OR(C5="",E5=""),"",E5/C5) -> 0.019721519 | G5: =IF(F5="","",IF(OR(D5="g",D5="ml"),F5*100,"")) -> 1.9721519
A6: Doces e bolos | B6: Creme de leite | C6: 200 | D6: g | E6: 3.85 | F6: =IF(OR(C6="",E6=""),"",E6/C6) -> 0.01925 | G6: =IF(F6="","",IF(OR(D6="g",D6="ml"),F6*100,"")) -> 1.925
A7: Doces e bolos | B7: Leite em pó Ninho | C7: 400 | D7: g | E7: 18.94 | F7: =IF(OR(C7="",E7=""),"",E7/C7) -> 0.04735 | G7: =IF(F7="","",IF(OR(D7="g",D7="ml"),F7*100,"")) -> 4.735
A8: Doces e bolos | B8: Cream cheese | C8: 300 | D8: g | E8: 15 | F8: =IF(OR(C8="",E8=""),"",E8/C8) -> 0.05 | G8: =IF(F8="","",IF(OR(D8="g",D8="ml"),F8*100,"")) -> 5
A9: Doces e bolos | B9: Doce de leite | C9: 400 | D9: g | E9: 13 | F9: =IF(OR(C9="",E9=""),"",E9/C9) -> 0.0325 | G9: =IF(F9="","",IF(OR(D9="g",D9="ml"),F9*100,"")) -> 3.25
A10: Doces e bolos | B10: Leite integral | C10: 1000 | D10: ml | E10: 6.79 | F10: =IF(OR(C10="",E10=""),"",E10/C10) -> 0.00679 | G10: =IF(F10="","",IF(OR(D10="g",D10="ml"),F10*100,"")) -> 0.679
A11: Doces e bolos | B11: Leite de coco | C11: 200 | D11: ml | E11: 5 | F11: =IF(OR(C11="",E11=""),"",E11/C11) -> 0.025 | G11: =IF(F11="","",IF(OR(D11="g",D11="ml"),F11*100,"")) -> 2.5
A12: Doces e bolos | B12: Chantilly | C12: 1000 | D12: ml | E12: 24 | F12: =IF(OR(C12="",E12=""),"",E12/C12) -> 0.024 | G12: =IF(F12="","",IF(OR(D12="g",D12="ml"),F12*100,"")) -> 2.4
A13: Doces e bolos | B13: Manteiga sem sal | C13: 200 | D13: g | E13: 13.9 | F13: =IF(OR(C13="",E13=""),"",E13/C13) -> 0.0695 | G13: =IF(F13="","",IF(OR(D13="g",D13="ml"),F13*100,"")) -> 6.95
A14: Doces e bolos | B14: Margarina | C14: 500 | D14: g | E14: 9 | F14: =IF(OR(C14="",E14=""),"",E14/C14) -> 0.018 | G14: =IF(F14="","",IF(OR(D14="g",D14="ml"),F14*100,"")) -> 1.8
A15: Doces e bolos | B15: Açúcar refinado | C15: 1000 | D15: g | E15: 4.34 | F15: =IF(OR(C15="",E15=""),"",E15/C15) -> 0.00434 | G15: =IF(F15="","",IF(OR(D15="g",D15="ml"),F15*100,"")) -> 0.434
A16: Doces e bolos | B16: Açúcar cristal | C16: 1000 | D16: g | E16: 3.47 | F16: =IF(OR(C16="",E16=""),"",E16/C16) -> 0.00347 | G16: =IF(F16="","",IF(OR(D16="g",D16="ml"),F16*100,"")) -> 0.347
... A58: Salgados | B58: Maionese | C58: 500 | D58: g | E58: 10 | F58: =IF(OR(C58="",E58=""),"",E58/C58) -> 0.02 | G58: =IF(F58="","",IF(OR(D58="g",D58="ml"),F58*100,"")) -> 2
A59: Salgados | B59: Temperos diversos | E59: 5 | F59: =IF(OR(C59="",E59=""),"",E59/C59) | G59: =IF(F59="","",IF(OR(D59="g",D59="ml"),F59*100,""))
A61: Observação | B61: 'Temperos diversos' não tem quantidade informada; preencha a coluna C para calcular o custo.

Sheet Embalagens
A1: Embalagens: custo unitário
A2: Custo por unidade = Preço ÷ Quantidade no pacote. Itens com quantidade vazia ainda precisam de tamanho informado.
A4: Item | B4: Qtd no pacote | C4: Preço (R$) | D4: Custo por unidade (R$)
A5: Forminha de acetato | B5: 100 | C5: 15 | D5: =IF(OR(B5="",C5=""),"",C5/B5) -> 0.15
A6: Caixa para 100 doces | B6: 1 | C6: 12 | D6: =IF(OR(B6="",C6=""),"",C6/B6) -> 12
A7: Sacola para entrega | B7: 50 | C7: 25 | D7: =IF(OR(B7="",C7=""),"",C7/B7) -> 0.5
A8: Pote para sobremesa | B8: 50 | C8: 35 | D8: =IF(OR(B8="",C8=""),"",C8/B8) -> 0.7
A9: Etiqueta personalizada com logomarca | B9: 100 | C9: 30 | D9: =IF(OR(B9="",C9=""),"",C9/B9) -> 0.3
A10: Papel para embalar picolé | B10: 100 | C10: 15 | D10: =IF(OR(B10="",C10=""),"",C10/B10) -> 0.15
A11: Saquinho individual para picolé | B11: 100 | C11: 12 | D11: =IF(OR(B11="",C11=""),"",C11/B11) -> 0.12
A12: Adesivo personalizado para picolé | B12: 100 | C12: 30 | D12: =IF(OR(B12="",C12=""),"",C12/B12) -> 0.3
A13: Placa de MDF para bolo | B13: 1 | C13: 8 | D13: =IF(OR(B13="",C13=""),"",C13/B13) -> 8
A14: Caixa para bolo | B14: 1 | C14: 6 | D14: =IF(OR(B14="",C14=""),"",C14/B14) -> 6
A15: Sacola para transporte | B15: 1 | C15: 0.5 | D15: =IF(OR(B15="",C15=""),"",C15/B15) -> 0.5
A16: Adesivo personalizado | B16: 1 | C16: 0.3 | D16: =IF(OR(B16="",C16=""),"",C16/B16) -> 0.3
A17: Papel-manteiga (rolo) | C17: 12 | D17: =IF(OR(B17="",C17=""),"",C17/B17)
A18: Filme plástico (rolo) | C18: 12 | D18: =IF(OR(B18="",C18=""),"",C18/B18)
A19: Papel-alumínio (rolo) | C19: 12 | D19: =IF(OR(B19="",C19=""),"",C19/B19)
A21: Observação | B21: Papel-manteiga, filme e papel-alumínio: informe o tamanho do rolo na coluna B.

Sheet Ficha Técnica
A1: Ficha técnica por produto
A2: Digite o nome do insumo ou embalagem exatamente como nas abas Insumos e Embalagens. Quantidade na unidade do item (g, ml ou un).
A3: Linhas de exemplo em azul podem ser apagadas e substituídas pelos seus produtos.
A4: Produto | B4: Insumo ou embalagem | C4: Quantidade usada | D4: Custo unitário (R$) | E4: Custo do item (R$) | F4: Custo total do produto (R$)
A5: Brigadeiro (exemplo) | B5: Leite condensado | C5: 395 | D5: =IF(B5="","",IFERROR(INDEX(Insumos!$F$5:$F$59,MATCH(B5,Insumos!$B$5:$B$59,0)),INDEX(Embalagens!$D$5:$D$19,MATCH(B5,Embalagens!$A$5:$A$19,0)))) -> 0.019721519 | E5: =IF(OR(C5="",D5=""),"",C5*D5) -> 7.79 | F5: =IF(A5="","",SUMIF($A$5:$A$104,A5,$E$5:$E$104)) -> 18.5825
A6: Brigadeiro (exemplo) | B6: Manteiga sem sal | C6: 15 | D6: =IF(B6="","",IFERROR(INDEX(Insumos!$F$5:$F$59,MATCH(B6,Insumos!$B$5:$B$59,0)),INDEX(Embalagens!$D$5:$D$19,MATCH(B6,Embalagens!$A$5:$A$19,0)))) -> 0.0695 | E6: =IF(OR(C6="",D6=""),"",C6*D6) -> 1.0425 | F6: =IF(A6="","",SUMIF($A$5:$A$104,A6,$E$5:$E$104)) -> 18.5825
A7: Brigadeiro (exemplo) | B7: Chocolate ao leite | C7: 200 | D7: =IF(B7="","",IFERROR(INDEX(Insumos!$F$5:$F$59,MATCH(B7,Insumos!$B$5:$B$59,0)),INDEX(Embalagens!$D$5:$D$19,MATCH(B7,Embalagens!$A$5:$A$19,0)))) -> 0.048 | E7: =IF(OR(C7="",D7=""),"",C7*D7) -> 9.6 | F7: =IF(A7="","",SUMIF($A$5:$A$104,A7,$E$5:$E$104)) -> 18.5825
A8: Brigadeiro (exemplo) | B8: Forminha de acetato | C8: 1 | D8: =IF(B8="","",IFERROR(INDEX(Insumos!$F$5:$F$59,MATCH(B8,Insumos!$B$5:$B$59,0)),INDEX(Embalagens!$D$5:$D$19,MATCH(B8,Embalagens!$A$5:$A$19,0)))) -> 0.15 | E8: =IF(OR(C8="",D8=""),"",C8*D8) -> 0.15 | F8: =IF(A8="","",SUMIF($A$5:$A$104,A8,$E$5:$E$104)) -> 18.5825
D9: =IF(B9="","",IFERROR(INDEX(Insumos!$F$5:$F$59,MATCH(B9,Insumos!$B$5:$B$59,0)),INDEX(Embalagens!$D$5:$D$19,MATCH(B9,Embalagens!$A$5:$A$19,0)))) | E9: =IF(OR(C9="",D9=""),"",C9*D9) | F9: =IF(A9="","",SUMIF($A$5:$A$104,A9,$E$5:$E$104))
D10: =IF(B10="","",IFERROR(INDEX(Insumos!$F$5:$F$59,MATCH(B10,Insumos!$B$5:$B$59,0)),INDEX(Embalagens!$D$5:$D$19,MATCH(B10,Embalagens!$A$5:$A$19,0)))) | E10: =IF(OR(C10="",D10=""),"",C10*D10) | F10: =IF(A10="","",SUMIF($A$5:$A$104,A10,$E$5:$E$104))
D11: =IF(B11="","",IFERROR(INDEX(Insumos!$F$5:$F$59,MATCH(B11,Insumos!$B$5:$B$59,0)),INDEX(Embalagens!$D$5:$D$19,MATCH(B11,Embalagens!$A$5:$A$19,0)))) | E11: =IF(OR(C11="",D11=""),"",C11*D11) | F11: =IF(A11="","",SUMIF($A$5:$A$104,A11,$E$5:$E$104))
D12: =IF(B12="","",IFERROR(INDEX(Insumos!$F$5:$F$59,MATCH(B12,Insumos!$B$5:$B$59,0)),INDEX(Embalagens!$D$5:$D$19,MATCH(B12,Embalagens!$A$5:$A$19,0)))) | E12: =IF(OR(C12="",D12=""),"",C12*D12) | F12: =IF(A12="","",SUMIF($A$5:$A$104,A12,$E$5:$E$104))
D13: =IF(B13="","",IFERROR(INDEX(Insumos!$F$5:$F$59,MATCH(B13,Insumos!$B$5:$B$59,0)),INDEX(Embalagens!$D$5:$D$19,MATCH(B13,Embalagens!$A$5:$A$19,0)))) | E13: =IF(OR(C13="",D13=""),"",C13*D13) | F13: =IF(A13="","",SUMIF($A$5:$A$104,A13,$E$5:$E$104))
D14: =IF(B14="","",IFERROR(INDEX(Insumos!$F$5:$F$59,MATCH(B14,Insumos!$B$5:$B$59,0)),INDEX(Embalagens!$D$5:$D$19,MATCH(B14,Embalagens!$A$5:$A$19,0)))) | E14: =IF(OR(C14="",D14=""),"",C14*D14) | F14: =IF(A14="","",SUMIF($A$5:$A$104,A14,$E$5:$E$104))
D15: =IF(B15="","",IFERROR(INDEX(Insumos!$F$5:$F$59,MATCH(B15,Insumos!$B$5:$B$59,0)),INDEX(Embalagens!$D$5:$D$19,MATCH(B15,Embalagens!$A$5:$A$19,0)))) | E15: =IF(OR(C15="",D15=""),"",C15*D15) | F15: =IF(A15="","",SUMIF($A$5:$A$104,A15,$E$5:$E$104))
D16: =IF(B16="","",IFERROR(INDEX(Insumos!$F$5:$F$59,MATCH(B16,Insumos!$B$5:$B$59,0)),INDEX(Embalagens!$D$5:$D$19,MATCH(B16,Embalagens!$A$5:$A$19,0)))) | E16: =IF(OR(C16="",D16=""),"",C16*D16) | F16: =IF(A16="","",SUMIF($A$5:$A$104,A16,$E$5:$E$104))
D17: =IF(B17="","",IFERROR(INDEX(Insumos!$F$5:$F$59,MATCH(B17,Insumos!$B$5:$B$59,0)),INDEX(Embalagens!$D$5:$D$19,MATCH(B17,Embalagens!$A$5:$A$19,0)))) | E17: =IF(OR(C17="",D17=""),"",C17*D17) | F17: =IF(A17="","",SUMIF($A$5:$A$104,A17,$E$5:$E$104))
D18: =IF(B18="","",IFERROR(INDEX(Insumos!$F$5:$F$59,MATCH(B18,Insumos!$B$5:$B$59,0)),INDEX(Embalagens!$D$5:$D$19,MATCH(B18,Embalagens!$A$5:$A$19,0)))) | E18: =IF(OR(C18="",D18=""),"",C18*D18) | F18: =IF(A18="","",SUMIF($A$5:$A$104,A18,$E$5:$E$104))
D19: =IF(B19="","",IFERROR(INDEX(Insumos!$F$5:$F$59,MATCH(B19,Insumos!$B$5:$B$59,0)),INDEX(Embalagens!$D$5:$D$19,MATCH(B19,Embalagens!$A$5:$A$19,0)))) | E19: =IF(OR(C19="",D19=""),"",C19*D19) | F19: =IF(A19="","",SUMIF($A$5:$A$104,A19,$E$5:$E$104))
D20: =IF(B20="","",IFERROR(INDEX(Insumos!$F$5:$F$59,MATCH(B20,Insumos!$B$5:$B$59,0)),INDEX(Embalagens!$D$5:$D$19,MATCH(B20,Embalagens!$A$5:$A$19,0)))) | E20: =IF(OR(C20="",D20=""),"",C20*D20) | F20: =IF(A20="","",SUMIF($A$5:$A$104,A20,$E$5:$E$104))
... D104: =IF(B104="","",IFERROR(INDEX(Insumos!$F$5:$F$59,MATCH(B104,Insumos!$B$5:$B$59,0)),INDEX(Embalagens!$D$5:$D$19,MATCH(B104,Embalagens!$A$5:$A$19,0)))) | E104: =IF(OR(C104="",D104=""),"",C104*D104) | F104: =IF(A104="","",SUMIF($A$5:$A$104,A104,$E$5:$E$104))
